<?xml version="1.0" encoding="UTF-8"?>
<objects serializationModel="Studio.02.02.00">
	<object class="AudioFile" id="{d1d56916-029c-4899-9c4d-cc52a8be850e}">
		<property name="assetPath">
			<value>SFX_ALL/Player/SFX_PLYR_AbilityReady.wav</value>
		</property>
		<property name="frequencyInKHz">
			<value>48</value>
		</property>
		<property name="channelCount">
			<value>1</value>
		</property>
		<property name="length">
			<value>0.68820833333333331</value>
		</property>
		<relationship name="masterAssetFolder">
			<destination>{ac5f5264-6d3e-4c54-93a0-f535a51777e4}</destination>
		</relationship>
	</object>
</objects>
