<?xml version="1.0" encoding="UTF-8"?>
<objects serializationModel="Studio.02.02.00">
	<object class="AudioFile" id="{f622bfb1-632a-480f-a9bb-c2b2fb839cac}">
		<property name="assetPath">
			<value>Placeholders/Music/PN81034_1_A_Legend_Rises_Main.mp3</value>
		</property>
		<property name="isStreaming">
			<value>true</value>
		</property>
		<property name="frequencyInKHz">
			<value>44.0999985</value>
		</property>
		<property name="channelCount">
			<value>2</value>
		</property>
		<property name="length">
			<value>184.39836734693878</value>
		</property>
		<relationship name="masterAssetFolder">
			<destination>{ac5f5264-6d3e-4c54-93a0-f535a51777e4}</destination>
		</relationship>
	</object>
</objects>
